sopel_http_example/__init__.py
sopel_http_example-0.1.1.dist-info/licenses/LICENSE.txt
sopel_http_example-0.1.1.dist-info/METADATA
sopel_http_example-0.1.1.dist-info/WHEEL
sopel_http_example-0.1.1.dist-info/entry_points.txt
sopel_http_example-0.1.1.dist-info/top_level.txt
sopel_http_example-0.1.1.dist-info/RECORD
