Metadata-Version: 2.4
Name: sopel-http-example
Version: 0.1.1
Summary: An example Sopel plugin making use of sopel-http
Author-email: Trevor Bergeron <mal@sec.gd>
Project-URL: HomePage, https://github.com/half-duplex/sopel-http-example
Keywords: irc,sopel,example
Classifier: Development Status :: 4 - Beta
Classifier: Intended Audience :: Developers
Classifier: License :: OSI Approved :: European Union Public Licence 1.2 (EUPL 1.2)
Classifier: Operating System :: OS Independent
Classifier: Topic :: Communications :: Chat :: Internet Relay Chat
Requires-Python: ~=3.9
License-File: LICENSE.txt
Requires-Dist: sopel~=7.1.9
Requires-Dist: sopel-http~=0.1.1
Requires-Dist: Flask~=2.1.2
Dynamic: license-file
